release_mate/__init__.py
release_mate/api.py
release_mate/cli.py
release_mate/templates/project/cookiecutter.json
release_mate/templates/project/{{cookiecutter.root_dir}}/{{cookiecutter.project_id}}.toml
release_mate-0.1.4.dist-info/LICENSE
release_mate-0.1.4.dist-info/METADATA
release_mate-0.1.4.dist-info/WHEEL
release_mate-0.1.4.dist-info/entry_points.txt
release_mate-0.1.4.dist-info/RECORD
